Metadata-Version: 2.1
Name: image_processing-annx3
Version: 0.0.4
Summary: Test version - Image processing. This project belongs to Karina Tiemi Kato, Tech Lead, Machine Learning Engineer, Data Scientist Specialist at Take. This package is a demo for simulation of upload on the Test Pypi website, and it's from class of the Bootcamp developer full stack Python. E-mail:karinatkato@gmail.com.
Home-page: https://github.com/anascunha/image-processing-package
Author: annx3
Author-email: ana.sara.sc@hotmail.com
Requires-Python: >=3.8
License-File: LICENSE.txt
Requires-Dist: matplotlib
Requires-Dist: numpy
Requires-Dist: scikit-image>=0.16.1
Requires-Dist: bleach==3.3.0
